HISTORY.rst
LICENSE.txt
MANIFEST.in
README.rst
ez_setup.py
requirements.txt
setup.cfg
setup.py
multyvac/__init__.py
multyvac/api_key.py
multyvac/cluster.py
multyvac/config.py
multyvac/job.py
multyvac/layer.py
multyvac/multyvac.py
multyvac/setup.py
multyvac/volume.py
multyvac/util/__init__.py
multyvac/util/cloudpickle.py
multyvac/util/cygwin.py
multyvac/util/module_dependency.py
multyvac/util/preinstalls.py
vac.egg-info/PKG-INFO
vac.egg-info/SOURCES.txt
vac.egg-info/dependency_links.txt
vac.egg-info/pbr.json
vac.egg-info/requires.txt
vac.egg-info/top_level.txt