Metadata-Version: 1.1
Name: vac
Version: 0.6.0
Summary: Multyvac fork for Python
Home-page: https://github.com/cloudpipe/multyvac-fork
Author: Cloudpipe
Author-email: cloudpipe@googlegroups.com
License: LICENSE.txt
Platform: CPython 2.6
Platform: CPython 2.7
Classifier: Development Status :: 4 - Beta
Classifier: Intended Audience :: Developers
Classifier: License :: OSI Approved :: BSD License
Classifier: Operating System :: POSIX
Classifier: Operating System :: Microsoft :: Windows
Classifier: Operating System :: MacOS :: MacOS X
Classifier: Programming Language :: Python :: 2.6
Classifier: Programming Language :: Python :: 2.7
Classifier: Topic :: Software Development :: Libraries :: Python Modules
Classifier: Topic :: Scientific/Engineering
Classifier: Topic :: System :: Distributed Computing
